<?xml version="1.0" encoding="UTF-8" standalone="no"?>
<!-- Generated 21-may-2019 11:53:53 by Hibernate Tools 5.3.6.Final --><!DOCTYPE hibernate-mapping PUBLIC "-//Hibernate/Hibernate Mapping DTD 3.0//EN" "http://www.hibernate.org/dtd/hibernate-mapping-3.0.dtd">
<hibernate-mapping auto-import="true" default-access="property" default-cascade="none" default-lazy="true">
    <class catalog="RESTAURANT" dynamic-insert="false" dynamic-update="false" mutable="true" name="MP14SMMA.SERVER.MODEL.Hasdish" optimistic-lock="version" polymorphism="implicit" select-before-update="false" table="hasdish">
        <composite-id class="MP14SMMA.SERVER.MODEL.HasdishId" mapped="false" name="id" unsaved-value="undefined">
            <key-property name="idTicket" type="int">
                <column name="id_ticket"/>
            </key-property>
            <key-property name="idItemDish" type="int">
                <column name="id_item_dish"/>
            </key-property>
        </composite-id>
        <property generated="never" lazy="false" name="quantityItem" optimistic-lock="true" type="java.lang.Integer" unique="false">
            <column name="quantity_item"/>
        </property>
    </class>
</hibernate-mapping>
